honeycomb/__init__.py
honeycomb/_generated_models.py
honeycomb/auth.py
honeycomb/cli/__init__.py
honeycomb/cli/api_keys.py
honeycomb/cli/auth.py
honeycomb/cli/boards.py
honeycomb/cli/columns.py
honeycomb/cli/config.py
honeycomb/cli/datasets.py
honeycomb/cli/derived_columns.py
honeycomb/cli/environments.py
honeycomb/cli/formatters.py
honeycomb/cli/markers.py
honeycomb/cli/queries.py
honeycomb/cli/recipients.py
honeycomb/cli/slos.py
honeycomb/cli/triggers.py
honeycomb/client.py
honeycomb/exceptions.py
honeycomb/mcp/__init__.py
honeycomb/mcp/__main__.py
honeycomb/mcp/server.py
honeycomb/models/__init__.py
honeycomb/models/api_keys.py
honeycomb/models/auth.py
honeycomb/models/board_builder.py
honeycomb/models/boards.py
honeycomb/models/burn_alerts.py
honeycomb/models/columns.py
honeycomb/models/datasets.py
honeycomb/models/derived_columns.py
honeycomb/models/environments.py
honeycomb/models/events.py
honeycomb/models/marker_builder.py
honeycomb/models/markers.py
honeycomb/models/queries.py
honeycomb/models/query_annotations.py
honeycomb/models/query_builder.py
honeycomb/models/recipient_builder.py
honeycomb/models/recipients.py
honeycomb/models/service_map_dependencies.py
honeycomb/models/slo_builder.py
honeycomb/models/slos.py
honeycomb/models/tags_mixin.py
honeycomb/models/tool_inputs.py
honeycomb/models/trigger_builder.py
honeycomb/models/triggers.py
honeycomb/resources/__init__.py
honeycomb/resources/_recipient_utils.py
honeycomb/resources/api_keys.py
honeycomb/resources/auth.py
honeycomb/resources/base.py
honeycomb/resources/boards.py
honeycomb/resources/burn_alerts.py
honeycomb/resources/columns.py
honeycomb/resources/datasets.py
honeycomb/resources/derived_columns.py
honeycomb/resources/environments.py
honeycomb/resources/events.py
honeycomb/resources/markers.py
honeycomb/resources/queries.py
honeycomb/resources/query_annotations.py
honeycomb/resources/query_results.py
honeycomb/resources/recipients.py
honeycomb/resources/service_map_dependencies.py
honeycomb_api-0.7.4.dist-info/METADATA
honeycomb_api-0.7.4.dist-info/WHEEL
honeycomb_api-0.7.4.dist-info/entry_points.txt
honeycomb_api-0.7.4.dist-info/licenses/LICENSE
honeycomb_api-0.7.4.dist-info/RECORD
