Metadata-Version: 2.4
Name: honeycomb-api
Version: 0.7.4
Summary: Python client for the Honeycomb.io API
License-Expression: MIT
License-File: LICENSE
Keywords: honeycomb,observability,api,client,sdk
Author: Irving Popovetsky
Requires-Python: >=3.10
Classifier: Development Status :: 3 - Alpha
Classifier: Intended Audience :: Developers
Classifier: Programming Language :: Python :: 3
Classifier: Programming Language :: Python :: 3.10
Classifier: Programming Language :: Python :: 3.11
Classifier: Programming Language :: Python :: 3.12
Classifier: Programming Language :: Python :: 3.13
Classifier: Typing :: Typed
Requires-Dist: cachetools (>=5.0)
Requires-Dist: httpx (>=0.27)
Requires-Dist: pydantic (>=2.0)
Requires-Dist: pytest-xdist (>=3.8.0,<4.0.0)
Requires-Dist: pyyaml (>=6.0)
Requires-Dist: rich (>=13.0)
Requires-Dist: typer (>=0.21.0)
Project-URL: Homepage, https://irvingpop.github.io/honeycomb-api-python/
Project-URL: Repository, https://github.com/irvingpop/honeycomb-api-python
